[
  {
    "id": "rumor_low_taxes",
    "text": "Whispers say the King plans to lower taxes... or raise them.",
    "emotion_tags": ["distrust", "curiosity"],
    "kingdom_tags": ["reform", "instability"],
    "level": ["village", "governor"],
    "intensity": "low",
    "visual": {
      "tag_ia": "peasants murmuring around village fire"
    }
  },
  {
    "id": "rumor_shadow_council",
    "text": "They say a secret council now guides the King’s decisions from the shadows.",
    "emotion_tags": ["fear", "distrust"],
    "kingdom_tags": ["power", "intrigue"],
    "level": ["royal_court", "mythical_kingdom"],
    "intensity": "medium",
    "visual": {
      "tag_ia": "hooded figures in dark chamber whispering behind throne"
    }
  },
  {
    "id": "rumor_return_of_heir",
    "text": "A traveler swears he saw the lost heir alive, deep in the snowy north.",
    "emotion_tags": ["hope", "confusion"],
    "kingdom_tags": ["legacy", "loyalty"],
    "level": ["governor", "mythical_kingdom"],
    "intensity": "high",
    "visual": {
      "tag_ia": "hooded figure with royal crest in snowy forest"
    }
  }
]
